pyobas/__init__.py
pyobas/_version.py
pyobas/base.py
pyobas/client.py
pyobas/exceptions.py
pyobas/mixins.py
pyobas/utils.py
pyobas-4.0.0.dist-info/LICENSE
pyobas-4.0.0.dist-info/METADATA
pyobas-4.0.0.dist-info/WHEEL
pyobas-4.0.0.dist-info/top_level.txt
pyobas-4.0.0.dist-info/RECORD
