Metadata-Version: 2.1
Name: pyobas
Version: 4.0.0
Summary: Python API client for OpenBAS.
Home-page: https://github.com/OpenBAS-Platform/client-python
Author: Filigran
Author-email: contact@filigran.io
Maintainer: Filigran
License: Apache
Classifier: Development Status :: 5 - Production/Stable
Classifier: Intended Audience :: Developers
Classifier: Intended Audience :: Information Technology
Classifier: Intended Audience :: Science/Research
Classifier: License :: OSI Approved :: Apache Software License
Classifier: Natural Language :: English
Classifier: Natural Language :: French
Classifier: Operating System :: OS Independent
Classifier: Programming Language :: Python :: 3
Classifier: Topic :: Security
Classifier: Topic :: Software Development :: Libraries :: Python Modules
Requires-Python: >=3.7
License-File: LICENSE
Requires-Dist: dataclasses-json ~=0.6.4
Requires-Dist: pika ~=1.3.1
Requires-Dist: prometheus-client ~=0.20.0
Requires-Dist: python-json-logger ~=2.0.4
Requires-Dist: pyyaml ~=6.0
Requires-Dist: requests ~=2.31.0
Requires-Dist: requests-toolbelt ~=1.0.0
Requires-Dist: setuptools ~=69.2.0
Provides-Extra: dev
Requires-Dist: black ~=24.3.0 ; extra == 'dev'
Requires-Dist: build ~=1.1.1 ; extra == 'dev'
Requires-Dist: isort ~=5.13.0 ; extra == 'dev'
Requires-Dist: types-pytz ~=2024.1.0.20240203 ; extra == 'dev'
Requires-Dist: pre-commit ~=3.6.0 ; extra == 'dev'
Requires-Dist: types-python-dateutil ~=2.9.0 ; extra == 'dev'
Requires-Dist: wheel ~=0.43.0 ; extra == 'dev'
Provides-Extra: doc
Requires-Dist: autoapi ~=2.0.1 ; extra == 'doc'
Requires-Dist: sphinx-autodoc-typehints ~=2.0.0 ; extra == 'doc'
Requires-Dist: sphinx-rtd-theme ~=2.0.0 ; extra == 'doc'
